MANIFEST.in
README.txt
setup.py
docs/HISTORY.txt
docs/LICENSE.txt
infrae/__init__.py
infrae.maildrophost.egg-info/PKG-INFO
infrae.maildrophost.egg-info/SOURCES.txt
infrae.maildrophost.egg-info/dependency_links.txt
infrae.maildrophost.egg-info/entry_points.txt
infrae.maildrophost.egg-info/namespace_packages.txt
infrae.maildrophost.egg-info/requires.txt
infrae.maildrophost.egg-info/top_level.txt
infrae/maildrophost/__init__.py
infrae/maildrophost/ctl.py
infrae/maildrophost/maildrop.py
infrae/maildrophost/stringparse.py