Metadata-Version: 1.0
Name: infrae.maildrophost
Version: 2.2
Summary: Recipe to install and setup maildrophost server
Home-page: http://www.python.org/pypi/infrae.maildrophost
Author: Sylvain Viollon
Author-email: info@infrae.com
License: ZPL 2.1
Keywords: maildrophost buildout
Platform: UNKNOWN
Classifier: Framework :: Buildout
